fullsubtractor/Full_Subtractor_3.v
module Full_Subtractor_3(output D, B, input X, Y, Z);
assign D = X ^ Y ^ Z;
assign B = ~X & (Y^Z) | Y & Z;
endmodule

fullsubtractor/Full_Subtractor_3_tb.v
`include "Full_Subtractor_3.v"
module Full_Subtractor_3_tb;
wire D, B;
reg X, Y, Z;
Full_Subtractor_3 Instance0 (D, B, X, Y, Z);
initial begin
    X = 0; Y = 0; Z = 0;
#1  X = 0; Y = 0; Z = 1;
#1  X = 0; Y = 1; Z = 0;
#1  X = 0; Y = 1; Z = 1;
#1  X = 1; Y = 0; Z = 0;
#1  X = 1; Y = 0; Z = 1;
#1  X = 1; Y = 1; Z = 0;
#1  X = 1; Y = 1; Z = 1; 
end
initial begin
    $monitor ("%t, X = %d| Y = %d| Z = %d| B = %d| D = %d", $time, X, Y, Z, B, D);
    $dumpfile("dump.vcd");
    $dumpvars();
end
endmodule

fullsubtractor/dump.vcd
$date
	Thu Aug 10 08:26:44 2023
$end
$version
	Icarus Verilog
$end
$timescale
	1s
$end
$scope module Full_Subtractor_3_tb $end
$var wire 1 ! D $end
$var wire 1 " B $end
$var reg 1 # X $end
$var reg 1 $ Y $end
$var reg 1 % Z $end
$scope module Instance0 $end
$var wire 1 " B $end
$var wire 1 ! D $end
$var wire 1 # X $end
$var wire 1 $ Y $end
$var wire 1 % Z $end
$upscope $end
$upscope $end
$enddefinitions $end
#0
$dumpvars
0%
0$
0#
0"
0!
$end
#1
1"
1!
1%
#2
0%
1$
#3
0!
1%
#4
0"
1!
0%
0$
1#
#5
0!
1%
#6
0%
1$
#7
1"
1!
1%
